README.rst
setup.py
pytest_gc/__init__.py
pytest_gc/plugin.py
pytest_gc.egg-info/PKG-INFO
pytest_gc.egg-info/SOURCES.txt
pytest_gc.egg-info/dependency_links.txt
pytest_gc.egg-info/entry_points.txt
pytest_gc.egg-info/requires.txt
pytest_gc.egg-info/top_level.txt