Metadata-Version: 1.1
Name: pytest-gc
Version: 0.0.1
Summary: The garbage collector plugin for py.test
Home-page: https://github.com/vtitor/pytest-gc
Author: Victor Titor
Author-email: vtitor.edumix@gmail.com
License: UNKNOWN
Platform: UNKNOWN
Classifier: Framework :: Pytest
Classifier: Programming Language :: Python
Classifier: Programming Language :: Python :: 2.7
Classifier: Programming Language :: Python :: 3.6
